README.txt
setup.py
docs/HISTORY.txt
docs/INSTALL.txt
docs/LICENSE.GPL
docs/LICENSE.txt
sixfeetup/__init__.py
sixfeetup.utils.egg-info/PKG-INFO
sixfeetup.utils.egg-info/SOURCES.txt
sixfeetup.utils.egg-info/dependency_links.txt
sixfeetup.utils.egg-info/entry_points.txt
sixfeetup.utils.egg-info/namespace_packages.txt
sixfeetup.utils.egg-info/not-zip-safe
sixfeetup.utils.egg-info/requires.txt
sixfeetup.utils.egg-info/top_level.txt
sixfeetup/utils/__init__.py
sixfeetup/utils/configure.zcml
sixfeetup/utils/helpers.py
sixfeetup/utils/tests.py
sixfeetup/utils/browser/__init__.py
sixfeetup/utils/browser/configure.zcml
sixfeetup/utils/browser/references.py