Metadata-Version: 1.1
Name: sixfeetup.utils
Version: 2.19
Summary: A collection of commonly used code snippets
Home-page: http://www.sixfeetup.com/
Author: Six Feet Up, Inc.
Author-email: info@sixfeetup.com
License: GPL
Keywords: plone zope utils
Platform: UNKNOWN
Classifier: Framework :: Plone
Classifier: Programming Language :: Python
Classifier: Topic :: Software Development :: Libraries :: Python Modules
